lds_pipelines/.DS_Store
lds_pipelines/__init__.py
lds_pipelines/core/__init__.py
lds_pipelines/core/api_processor.py
lds_pipelines/core/case-1.csv
lds_pipelines/core/case-2.csv
lds_pipelines/core/case-3.csv
lds_pipelines/core/csv_processor.py
lds_pipelines/core/mock_api_data.csv
lds_pipelines/core/sprt_detector.py
lds_pipelines/dashboard/.DS_Store
lds_pipelines/dashboard/__init__.py
lds_pipelines/dashboard/api_page.py
lds_pipelines/dashboard/app.py
lds_pipelines/dashboard/csv_page.py
lds_pipelines/dashboard/intro_page.py
lds_pipelines/dashboard/static_pipeline.jpg
lds_pipelines/database/__init__.py
lds_pipelines/visualization/__init__.py
lds_pipelines/visualization/plotly_charts.py
lds_pipelines-0.3.0.dist-info/METADATA
lds_pipelines-0.3.0.dist-info/WHEEL
lds_pipelines-0.3.0.dist-info/entry_points.txt
lds_pipelines-0.3.0.dist-info/RECORD
