Metadata-Version: 2.1
Name: lds_pipelines
Version: 0.3.0
Summary: A tool to analyze the leakage in an pipeline using modified SPRT technique
Author: Aman Sharma
Requires-Python: >=3.12,<4.0
Classifier: Programming Language :: Python :: 3
Classifier: Programming Language :: Python :: 3.12
Classifier: Programming Language :: Python :: 3.13
Requires-Dist: matplotlib (>=3.10.1,<4.0.0)
Requires-Dist: numpy (>=2.2.4,<3.0.0)
Requires-Dist: pandas (>=2.2.3,<3.0.0)
Requires-Dist: plotly (>=6.0.1,<7.0.0)
Requires-Dist: pyarrow (>=19.0.1,<20.0.0)
Requires-Dist: requests (>=2.32.3,<3.0.0)
Requires-Dist: setuptools (>=78.1.0,<79.0.0)
Requires-Dist: st-autorefresh (>=0.1.0,<0.2.0)
Requires-Dist: streamlit (>=1.44.0,<2.0.0)
Requires-Dist: streamlit-autorefresh (>=1.0.1,<2.0.0)
